enigma_hiratsuca_maluli/__init__.py
enigma_hiratsuca_maluli/main.py
enigma_hiratsuca_maluli-0.0.1.dist-info/METADATA
enigma_hiratsuca_maluli-0.0.1.dist-info/WHEEL
enigma_hiratsuca_maluli-0.0.1.dist-info/top_level.txt
enigma_hiratsuca_maluli-0.0.1.dist-info/RECORD
